{"cameraMode":{"drawMode":0,"name":"Shaded","section":"Shading Mode"},"sceneLighting":false,"audioPlay":false,"sceneViewState":{"showFog":true,"showMaterialUpdate":true,"showSkybox":false,"showFlares":true,"showImageEffects":true,"showParticleSystems":true,"showVisualEffectGraphs":true,"m_FxEnabled":true},"in2DMode":false,"pivot":{"x":1.4156103134155274e-7,"y":0.08897896856069565,"z":0.0},"rotation":{"x":0.21220096945762635,"y":-0.43337735533714297,"z":0.10585866123437882,"w":0.8695335984230042},"size":0.35195720195770266,"orthographic":false}